ArriveTheSpaceship/__init__.py
ArriveTheSpaceship/__main__.py
ArriveTheSpaceship/media/images/monkey/alive.png
ArriveTheSpaceship/media/images/monkey/dead.png
ArriveTheSpaceship/media/images/monkey/hurt.png
ArriveTheSpaceship/media/images/obstacles/red-asteroid.png
ArriveTheSpaceship/media/images/surfaces/moon.jpg
ArriveTheSpaceship/media/monkey/alive.png
ArriveTheSpaceship/media/monkey/dead.png
ArriveTheSpaceship/media/monkey/hurt.png
ArriveTheSpaceship/media/obstacles/red-asteroid.png
ArriveTheSpaceship/media/surfaces/moon.jpg
ArriveTheSpaceship/src/__init__.py
ArriveTheSpaceship/src/display.py
ArriveTheSpaceship/src/tools.py
ArriveTheSpaceship-0.0.2.dist-info/LICENSE
ArriveTheSpaceship-0.0.2.dist-info/METADATA
ArriveTheSpaceship-0.0.2.dist-info/WHEEL
ArriveTheSpaceship-0.0.2.dist-info/entry_points.txt
ArriveTheSpaceship-0.0.2.dist-info/top_level.txt
ArriveTheSpaceship-0.0.2.dist-info/RECORD
