Metadata-Version: 2.1
Name: ArriveTheSpaceship
Version: 0.0.2
Summary: A frogger-like game made with Pygame
Home-page: https://github.com/viniciussousaazevedo/arrive_the_spaceship
Author: Vinícius Azevedo
Author-email: sousa0240@gmail.com
License: UNKNOWN
Platform: UNKNOWN
Classifier: Programming Language :: Python :: 3
Classifier: License :: OSI Approved :: MIT License
Classifier: Operating System :: Unix
Requires-Python: >=3.6
Requires-Dist: pygame (>=2.0)
